actigamma/__init__.py
actigamma/core.py
actigamma/database.py
actigamma/decorators.py
actigamma/exceptions.py
actigamma/identifier.py
actigamma/inventory.py
actigamma/util.py
actigamma/data/lines_decay_2012.min.json
actigamma-0.1.5.dist-info/LICENSE
actigamma-0.1.5.dist-info/METADATA
actigamma-0.1.5.dist-info/WHEEL
actigamma-0.1.5.dist-info/top_level.txt
actigamma-0.1.5.dist-info/RECORD
